Metadata-Version: 2.1
Name: redditmirror
Version: 1.0.0
Summary: Takes posts from your Reddit saved tab and x-posts them to a subreddit of your choice.
Home-page: https://github.com/mccreery/reddit-mirror
Author: Sam McCreery
Author-email: 4602020+mccreery@users.noreply.github.com
License: MIT
Platform: UNKNOWN
Classifier: Programming Language :: Python :: 3
Classifier: Operating System :: OS Independent
Classifier: License :: OSI Approved :: MIT License
